{
  "type": "forge:conditional",
  "recipes": [
    {
      "conditions": [
        {
          "type": "forge:mod_loaded",
          "modid": "twigs"
        }
      ],
      "recipe": {
        "type": "minecraft:crafting_shaped",
        "key": {
          "#": {
            "item": "biomesoplenty:hellbark_slab"
          },
          "I": {
            "item": "biomesoplenty:hellbark_fence"
          }
        },
        "pattern": [
          "###",
          "I I",
          "I I"
        ],
        "result": {
          "item": "compatoplenty:hellbark_table"
        }
      }
    }
  ]
}